flask_restx/__about__.py
flask_restx/__init__.py
flask_restx/_http.py
flask_restx/api.py
flask_restx/apidoc.py
flask_restx/cors.py
flask_restx/errors.py
flask_restx/fields.py
flask_restx/inputs.py
flask_restx/marshalling.py
flask_restx/mask.py
flask_restx/model.py
flask_restx/namespace.py
flask_restx/postman.py
flask_restx/representations.py
flask_restx/reqparse.py
flask_restx/resource.py
flask_restx/swagger.py
flask_restx/utils.py
flask_restx/schemas/__init__.py
flask_restx/schemas/oas-2.0.json
flask_restx/static/droid-sans.css
flask_restx/static/favicon-16x16.png
flask_restx/static/favicon-32x32.png
flask_restx/static/oauth2-redirect.html
flask_restx/static/swagger-ui-bundle.js
flask_restx/static/swagger-ui-bundle.js.map
flask_restx/static/swagger-ui-es-bundle-core.js
flask_restx/static/swagger-ui-es-bundle-core.js.map
flask_restx/static/swagger-ui-es-bundle.js
flask_restx/static/swagger-ui-es-bundle.js.map
flask_restx/static/swagger-ui-standalone-preset.js
flask_restx/static/swagger-ui-standalone-preset.js.map
flask_restx/static/swagger-ui.css
flask_restx/static/swagger-ui.css.map
flask_restx/static/swagger-ui.js
flask_restx/static/swagger-ui.js.map
flask_restx/static/files/.npmignore
flask_restx/static/files/droid-sans-latin-400.woff
flask_restx/static/files/droid-sans-latin-400.woff2
flask_restx/static/files/droid-sans-latin-700.woff
flask_restx/static/files/droid-sans-latin-700.woff2
flask_restx/templates/swagger-ui-css.html
flask_restx/templates/swagger-ui-libs.html
flask_restx/templates/swagger-ui.html
flask_restx-1.1.0.dist-info/LICENSE
flask_restx-1.1.0.dist-info/METADATA
flask_restx-1.1.0.dist-info/WHEEL
flask_restx-1.1.0.dist-info/top_level.txt
flask_restx-1.1.0.dist-info/RECORD
