Metadata-Version: 2.1
Name: flask-restx
Version: 1.1.0
Summary: Fully featured framework for fast, easy and documented API development with Flask
Home-page: https://github.com/python-restx/flask-restx
Author: python-restx Authors
License: BSD-3-Clause
Keywords: flask restx rest api swagger openapi
Platform: UNKNOWN
Classifier: Development Status :: 5 - Production/Stable
Classifier: Programming Language :: Python
Classifier: Environment :: Web Environment
Classifier: Operating System :: OS Independent
Classifier: Intended Audience :: Developers
Classifier: Topic :: System :: Software Distribution
Classifier: Programming Language :: Python
Classifier: Programming Language :: Python :: 3
Classifier: Programming Language :: Python :: 3.7
Classifier: Programming Language :: Python :: 3.8
Classifier: Programming Language :: Python :: 3.9
Classifier: Programming Language :: Python :: 3.10
Classifier: Programming Language :: Python :: 3.11
Classifier: Programming Language :: Python :: Implementation :: PyPy
Classifier: Topic :: Software Development :: Libraries :: Python Modules
Classifier: License :: OSI Approved :: BSD License
Provides-Extra: test
Provides-Extra: doc
Provides-Extra: dev
